t3SphinxThemeRtd/layout.html
t3SphinxThemeRtd/footer.html
t3SphinxThemeRtd/theme.conf
t3SphinxThemeRtd/breadcrumbs.html
t3SphinxThemeRtd/layout_old.html
t3SphinxThemeRtd/__init__.pyc
t3SphinxThemeRtd/versions.html
t3SphinxThemeRtd/searchbox.html
t3SphinxThemeRtd/search.html
t3SphinxThemeRtd/sitemap.html
t3SphinxThemeRtd/extensions.html
t3SphinxThemeRtd/__init__.py
t3SphinxThemeRtd/__pycache__/__init__.cpython-34.pyc
t3SphinxThemeRtd/static/jquery.min.map
t3SphinxThemeRtd/static/searchtools-ORIGINAL.js
t3SphinxThemeRtd/static/searchtools.js
t3SphinxThemeRtd/static/t3SphinxThemeRtd-3.6.15.txt
t3SphinxThemeRtd/static/jquery.js
t3SphinxThemeRtd/static/jquery-1.11.3.js
t3SphinxThemeRtd/static/jquery.min.js
t3SphinxThemeRtd/static/js/t3autocomplete.js
t3SphinxThemeRtd/static/js/t3autocomplete2.js
t3SphinxThemeRtd/static/js/modernizr.min.js
t3SphinxThemeRtd/static/js/theme.js
t3SphinxThemeRtd/static/img/typo3-documentation.png
t3SphinxThemeRtd/static/img/typo3-white.svg
t3SphinxThemeRtd/static/fonts/Lato-Regular.ttf
t3SphinxThemeRtd/static/fonts/FontAwesome.otf
t3SphinxThemeRtd/static/fonts/Share-Regular.ttf
t3SphinxThemeRtd/static/fonts/RobotoSlab-Bold.ttf
t3SphinxThemeRtd/static/fonts/fontawesome-webfont.ttf
t3SphinxThemeRtd/static/fonts/Share-TechMono.ttf
t3SphinxThemeRtd/static/fonts/Inconsolata-Bold.ttf
t3SphinxThemeRtd/static/fonts/Lato-Bold.ttf
t3SphinxThemeRtd/static/fonts/Share-BoldItalic.ttf
t3SphinxThemeRtd/static/fonts/fontawesome-webfont.woff
t3SphinxThemeRtd/static/fonts/Inconsolata.ttf
t3SphinxThemeRtd/static/fonts/fontawesome-webfont.eot
t3SphinxThemeRtd/static/fonts/Share-Bold.ttf
t3SphinxThemeRtd/static/fonts/Share-Italic.ttf
t3SphinxThemeRtd/static/fonts/fontawesome-webfont.svg
t3SphinxThemeRtd/static/fonts/RobotoSlab-Regular.ttf
t3SphinxThemeRtd/static/fonts/SourceCodePro/otf/SourceCodePro-Regular.otf
t3SphinxThemeRtd/static/fonts/SourceCodePro/otf/SourceCodePro-Bold.otf
t3SphinxThemeRtd-3.6.15.dist-info/DESCRIPTION.rst
t3SphinxThemeRtd-3.6.15.dist-info/WHEEL
t3SphinxThemeRtd-3.6.15.dist-info/metadata.json
t3SphinxThemeRtd-3.6.15.dist-info/METADATA
t3SphinxThemeRtd-3.6.15.dist-info/top_level.txt
t3SphinxThemeRtd-3.6.15.dist-info/RECORD
