Metadata-Version: 2.0
Name: t3SphinxThemeRtd
Version: 3.6.15
Summary: Docs.TYPO3.Org theme for Sphinx, starting 2015.
Home-page: https://github.com/TYPO3-Documentation/t3SphinxThemeRtd
Author: Martin Bless
Author-email: martin@mbless.de
License: MIT
Platform: UNKNOWN
Classifier: Development Status :: 5 - Production/Stable
Classifier: Intended Audience :: End Users/Desktop
Classifier: Framework :: Sphinx :: Extension
Classifier: License :: OSI Approved :: MIT License
Classifier: Programming Language :: Python :: 2.7
Classifier: Programming Language :: Python :: 3
Classifier: Operating System :: OS Independent
Classifier: Topic :: Documentation
Classifier: Topic :: Software Development :: Documentation
